Workbook

Sheet employees_raw
A1: Employee_ID | B1: Full_Name | C1: Department | D1: Job_Title | E1: Hire_Date | F1: Base_Salary_USD | G1: Performance_Rating | H1: Pay Grade | I1: Market Median | J1: Compa-Ratio | K1: Proposed Increase % | L1: 0.03
A2: EMP001 | B2: Sarah Connor | C2: Engineering | D2: Senior Software Engineer | E2: 1/15/2021 | F2: 135000 | G2: 4 | H2: =_xlfn.XLOOKUP(D2, job_mapping!$A$2:$A$9, job_mapping!$B$2:$B$9, "Not Found") -> G3 | I2: =_xlfn.XLOOKUP(H2, market_bands!$A$2:$A$5, market_bands!$C$2:$C$5, "Error") -> 130000 | J2: =Sheet1[[#This Row],[Base_Salary_USD]]/Sheet1[[#This Row],[Market Median]] -> 1.0384615 | K2: Current Total Payroll | L2: =SUM(Sheet1[Base_Salary_USD]) -> 1069000
A3: EMP002 | B3: Marcus Johnson | C3: Sales | D3: Account Executive | E3: 44567 | F3: 82000 | G3: 3 | H3: =_xlfn.XLOOKUP(D3, job_mapping!$A$2:$A$9, job_mapping!$B$2:$B$9, "Not Found") -> G2 | I3: =_xlfn.XLOOKUP(H3, market_bands!$A$2:$A$5, market_bands!$C$2:$C$5, "Error") -> 90000 | J3: =Sheet1[[#This Row],[Base_Salary_USD]]/Sheet1[[#This Row],[Market Median]] -> 0.91111111 | K3: Projected Total Payroll | L3: =L2*(1+L1) -> 1101070
A4: EMP003 | B4: Emily Chen | C4: Operations | D4: Operations Analyst | E4: 45200 | F4: 58000 | G4: 5 | H4: =_xlfn.XLOOKUP(D4, job_mapping!$A$2:$A$9, job_mapping!$B$2:$B$9, "Not Found") -> G1 | I4: =_xlfn.XLOOKUP(H4, market_bands!$A$2:$A$5, market_bands!$C$2:$C$5, "Error") -> 65000 | J4: =Sheet1[[#This Row],[Base_Salary_USD]]/Sheet1[[#This Row],[Market Median]] -> 0.89230769 | K4: Total Cost to Budget | L4: =L3-L2 -> 32070
A5: EMP004 | B5: David Miller | C5: Engineering | D5: Software Engineer | E5: 8/22/2023 | F5: 91000 | G5: 3 | H5: =_xlfn.XLOOKUP(D5, job_mapping!$A$2:$A$9, job_mapping!$B$2:$B$9, "Not Found") -> G2 | I5: =_xlfn.XLOOKUP(H5, market_bands!$A$2:$A$5, market_bands!$C$2:$C$5, "Error") -> 90000 | J5: =Sheet1[[#This Row],[Base_Salary_USD]]/Sheet1[[#This Row],[Market Median]] -> 1.0111111
A6: EMP005 | B6: Sophia Patel | C6: HR | D6: HR Manager | E6: 2/14/2020 | F6: 142000 | G6: 4 | H6: =_xlfn.XLOOKUP(D6, job_mapping!$A$2:$A$9, job_mapping!$B$2:$B$9, "Not Found") -> G3 | I6: =_xlfn.XLOOKUP(H6, market_bands!$A$2:$A$5, market_bands!$C$2:$C$5, "Error") -> 130000 | J6: =Sheet1[[#This Row],[Base_Salary_USD]]/Sheet1[[#This Row],[Market Median]] -> 1.0923077 | L6: =L4 -> 32070
A7: EMP006 | B7: James Wilson | C7: Sales | D7: Sales Director | E7: 43596 | F7: 195000 | G7: 5 | H7: =_xlfn.XLOOKUP(D7, job_mapping!$A$2:$A$9, job_mapping!$B$2:$B$9, "Not Found") -> G4 | I7: =_xlfn.XLOOKUP(H7, market_bands!$A$2:$A$5, market_bands!$C$2:$C$5, "Error") -> 190000 | J7: =Sheet1[[#This Row],[Base_Salary_USD]]/Sheet1[[#This Row],[Market Median]] -> 1.0263158 | K7: 0.02 | L7: 21380
A8: EMP007 | B8: Chloe Davis | C8: Engineering | D8: Software Engineer | E8: 45294 | F8: 88000 | G8: 3 | H8: =_xlfn.XLOOKUP(D8, job_mapping!$A$2:$A$9, job_mapping!$B$2:$B$9, "Not Found") -> G2 | I8: =_xlfn.XLOOKUP(H8, market_bands!$A$2:$A$5, market_bands!$C$2:$C$5, "Error") -> 90000 | J8: =Sheet1[[#This Row],[Base_Salary_USD]]/Sheet1[[#This Row],[Market Median]] -> 0.97777778 | K8: 0.03 | L8: 32070
A9: EMP008 | B9: Robert Taylor | C9: Operations | D9: Operations Manager | E9: 5/18/2021 | F9: 128000 | G9: 3 | H9: =_xlfn.XLOOKUP(D9, job_mapping!$A$2:$A$9, job_mapping!$B$2:$B$9, "Not Found") -> G3 | I9: =_xlfn.XLOOKUP(H9, market_bands!$A$2:$A$5, market_bands!$C$2:$C$5, "Error") -> 130000 | J9: =Sheet1[[#This Row],[Base_Salary_USD]]/Sheet1[[#This Row],[Market Median]] -> 0.98461538 | K9: 0.04 | L9: 42760
A10: EMP009 | B10: Mia Anderson | C10: HR | D10: HR Generalist | E10: 9/30/2022 | F10: 71000 | G10: 4 | H10: =_xlfn.XLOOKUP(D10, job_mapping!$A$2:$A$9, job_mapping!$B$2:$B$9, "Not Found") -> G1 | I10: =_xlfn.XLOOKUP(H10, market_bands!$A$2:$A$5, market_bands!$C$2:$C$5, "Error") -> 65000 | J10: =Sheet1[[#This Row],[Base_Salary_USD]]/Sheet1[[#This Row],[Market Median]] -> 1.0923077 | K10: 0.05 | L10: 53450
A11: EMP010 | B11: William Thomas | C11: Sales | D11: Account Executive | E11: 45264 | F11: 79000 | G11: 2 | H11: =_xlfn.XLOOKUP(D11, job_mapping!$A$2:$A$9, job_mapping!$B$2:$B$9, "Not Found") -> G2 | I11: =_xlfn.XLOOKUP(H11, market_bands!$A$2:$A$5, market_bands!$C$2:$C$5, "Error") -> 90000 | J11: =Sheet1[[#This Row],[Base_Salary_USD]]/Sheet1[[#This Row],[Market Median]] -> 0.87777778

Sheet job_mapping
A1: Official_Job_Title | B1: Pay_Grade
A2: Operations Analyst | B2: G1
A3: HR Generalist | B3: G1
A4: Account Executive | B4: G2
A5: Software Engineer | B5: G2
A6: HR Manager | B6: G3
A7: Senior Software Engineer | B7: G3
A8: Operations Manager | B8: G3
A9: Sales Director | B9: G4

Sheet market_bands
A1: Pay_Grade | B1: Band_Minimum | C1: Market_Median | D1: Band_Maximum
A2: G1 | B2: 55000 | C2: 65000 | D2: 75000
A3: G2 | B3: 75000 | C3: 90000 | D3: 105000
A4: G3 | B4: 110000 | C4: 130000 | D4: 150000
A5: G4 | B5: 160000 | C5: 190000 | D5: 220000
